pygelbooru/__init__.py
pygelbooru/gelbooru.py
pygelbooru-1.0.0.dist-info/LICENSE
pygelbooru-1.0.0.dist-info/METADATA
pygelbooru-1.0.0.dist-info/WHEEL
pygelbooru-1.0.0.dist-info/top_level.txt
pygelbooru-1.0.0.dist-info/RECORD
