Metadata-Version: 2.1
Name: pygelbooru
Version: 1.0.0
Summary: PyGelbooru is an unofficial and lightweight asynchronous library for Gelbooru compatible API's.
Home-page: https://github.com/FujiMakoto/pygelbooru
Download-URL: https://github.com/FujiMakoto/pygelbooru/archive/v0.5.0.tar.gz
Author: Makoto
Author-email: FujiMakoto@users.noreply.github.com
License: gpl-3.0
Keywords: gelbooru,anime,artwork,anime artwork,booru
Classifier: Development Status :: 4 - Beta
Classifier: Intended Audience :: Developers
Classifier: Topic :: Multimedia :: Graphics
Classifier: Topic :: Software Development :: Libraries :: Python Modules
Classifier: License :: OSI Approved :: GNU General Public License v3 (GPLv3)
Classifier: Programming Language :: Python :: 3.6
Classifier: Programming Language :: Python :: 3.7
Classifier: Programming Language :: Python :: 3.8
License-File: LICENSE
Requires-Dist: aiohttp
Requires-Dist: furl
Requires-Dist: xmltodict
